Workbook

Sheet 📊 Dashboard Anual
B2: FREELANCE FINANCE HUB 2026
B3: Control fiscal y financiero para autónomos y freelancers en España
B5: INGRESOS TOTALES (BASE) | E5: GASTOS TOTALES (BASE) | H5: BENEFICIO NETO ANTES IMPUESTOS | K5: PREVISIÓN IVA A PAGAR (HACIENDA)
B6: =SUM('💰 Ingresos'!E5:E100) | E6: =SUM('📉 Gastos'!E5:E100) | H6: =B6-E6 | K6: =SUM('💰 Ingresos'!G5:G100)-SUM('📉 Gastos'!F5:F100)
B9: Mes | C9: Ingresos Brutos | D9: Gastos Totales | E9: Beneficio Neto | F9: IVA Repercutido | G9: IVA Soportado
B10: Enero | C10: =SUMIFS('💰 Ingresos'!E:E, '💰 Ingresos'!A:A, ">="&DATE(2026,1,1), '💰 Ingresos'!A:A, "<="&EOMONTH(DATE(2026,1,1),0)) | D10: =SUMIFS('📉 Gastos'!E:E, '📉 Gastos'!A:A, ">="&DATE(2026,1,1), '📉 Gastos'!A:A, "<="&EOMONTH(DATE(2026,1,1),0)) | E10: =C10-D10 | F10: =SUMIFS('💰 Ingresos'!G:G, '💰 Ingresos'!A:A, ">="&DATE(2026,1,1), '💰 Ingresos'!A:A, "<="&EOMONTH(DATE(2026,1,1),0)) | G10: =SUMIFS('📉 Gastos'!F:F, '📉 Gastos'!A:A, ">="&DATE(2026,1,1), '📉 Gastos'!A:A, "<="&EOMONTH(DATE(2026,1,1),0))
B11: Febrero | C11: =SUMIFS('💰 Ingresos'!E:E, '💰 Ingresos'!A:A, ">="&DATE(2026,2,1), '💰 Ingresos'!A:A, "<="&EOMONTH(DATE(2026,2,1),0)) | D11: =SUMIFS('📉 Gastos'!E:E, '📉 Gastos'!A:A, ">="&DATE(2026,2,1), '📉 Gastos'!A:A, "<="&EOMONTH(DATE(2026,2,1),0)) | E11: =C11-D11 | F11: =SUMIFS('💰 Ingresos'!G:G, '💰 Ingresos'!A:A, ">="&DATE(2026,2,1), '💰 Ingresos'!A:A, "<="&EOMONTH(DATE(2026,2,1),0)) | G11: =SUMIFS('📉 Gastos'!F:F, '📉 Gastos'!A:A, ">="&DATE(2026,2,1), '📉 Gastos'!A:A, "<="&EOMONTH(DATE(2026,2,1),0))
B12: Marzo | C12: =SUMIFS('💰 Ingresos'!E:E, '💰 Ingresos'!A:A, ">="&DATE(2026,3,1), '💰 Ingresos'!A:A, "<="&EOMONTH(DATE(2026,3,1),0)) | D12: =SUMIFS('📉 Gastos'!E:E, '📉 Gastos'!A:A, ">="&DATE(2026,3,1), '📉 Gastos'!A:A, "<="&EOMONTH(DATE(2026,3,1),0)) | E12: =C12-D12 | F12: =SUMIFS('💰 Ingresos'!G:G, '💰 Ingresos'!A:A, ">="&DATE(2026,3,1), '💰 Ingresos'!A:A, "<="&EOMONTH(DATE(2026,3,1),0)) | G12: =SUMIFS('📉 Gastos'!F:F, '📉 Gastos'!A:A, ">="&DATE(2026,3,1), '📉 Gastos'!A:A, "<="&EOMONTH(DATE(2026,3,1),0))
B13: Abril | C13: =SUMIFS('💰 Ingresos'!E:E, '💰 Ingresos'!A:A, ">="&DATE(2026,4,1), '💰 Ingresos'!A:A, "<="&EOMONTH(DATE(2026,4,1),0)) | D13: =SUMIFS('📉 Gastos'!E:E, '📉 Gastos'!A:A, ">="&DATE(2026,4,1), '📉 Gastos'!A:A, "<="&EOMONTH(DATE(2026,4,1),0)) | E13: =C13-D13 | F13: =SUMIFS('💰 Ingresos'!G:G, '💰 Ingresos'!A:A, ">="&DATE(2026,4,1), '💰 Ingresos'!A:A, "<="&EOMONTH(DATE(2026,4,1),0)) | G13: =SUMIFS('📉 Gastos'!F:F, '📉 Gastos'!A:A, ">="&DATE(2026,4,1), '📉 Gastos'!A:A, "<="&EOMONTH(DATE(2026,4,1),0))
B14: Mayo | C14: =SUMIFS('💰 Ingresos'!E:E, '💰 Ingresos'!A:A, ">="&DATE(2026,5,1), '💰 Ingresos'!A:A, "<="&EOMONTH(DATE(2026,5,1),0)) | D14: =SUMIFS('📉 Gastos'!E:E, '📉 Gastos'!A:A, ">="&DATE(2026,5,1), '📉 Gastos'!A:A, "<="&EOMONTH(DATE(2026,5,1),0)) | E14: =C14-D14 | F14: =SUMIFS('💰 Ingresos'!G:G, '💰 Ingresos'!A:A, ">="&DATE(2026,5,1), '💰 Ingresos'!A:A, "<="&EOMONTH(DATE(2026,5,1),0)) | G14: =SUMIFS('📉 Gastos'!F:F, '📉 Gastos'!A:A, ">="&DATE(2026,5,1), '📉 Gastos'!A:A, "<="&EOMONTH(DATE(2026,5,1),0))
B15: Junio | C15: =SUMIFS('💰 Ingresos'!E:E, '💰 Ingresos'!A:A, ">="&DATE(2026,6,1), '💰 Ingresos'!A:A, "<="&EOMONTH(DATE(2026,6,1),0)) | D15: =SUMIFS('📉 Gastos'!E:E, '📉 Gastos'!A:A, ">="&DATE(2026,6,1), '📉 Gastos'!A:A, "<="&EOMONTH(DATE(2026,6,1),0)) | E15: =C15-D15 | F15: =SUMIFS('💰 Ingresos'!G:G, '💰 Ingresos'!A:A, ">="&DATE(2026,6,1), '💰 Ingresos'!A:A, "<="&EOMONTH(DATE(2026,6,1),0)) | G15: =SUMIFS('📉 Gastos'!F:F, '📉 Gastos'!A:A, ">="&DATE(2026,6,1), '📉 Gastos'!A:A, "<="&EOMONTH(DATE(2026,6,1),0))
B16: Julio | C16: =SUMIFS('💰 Ingresos'!E:E, '💰 Ingresos'!A:A, ">="&DATE(2026,7,1), '💰 Ingresos'!A:A, "<="&EOMONTH(DATE(2026,7,1),0)) | D16: =SUMIFS('📉 Gastos'!E:E, '📉 Gastos'!A:A, ">="&DATE(2026,7,1), '📉 Gastos'!A:A, "<="&EOMONTH(DATE(2026,7,1),0)) | E16: =C16-D16 | F16: =SUMIFS('💰 Ingresos'!G:G, '💰 Ingresos'!A:A, ">="&DATE(2026,7,1), '💰 Ingresos'!A:A, "<="&EOMONTH(DATE(2026,7,1),0)) | G16: =SUMIFS('📉 Gastos'!F:F, '📉 Gastos'!A:A, ">="&DATE(2026,7,1), '📉 Gastos'!A:A, "<="&EOMONTH(DATE(2026,7,1),0))
B17: Agosto | C17: =SUMIFS('💰 Ingresos'!E:E, '💰 Ingresos'!A:A, ">="&DATE(2026,8,1), '💰 Ingresos'!A:A, "<="&EOMONTH(DATE(2026,8,1),0)) | D17: =SUMIFS('📉 Gastos'!E:E, '📉 Gastos'!A:A, ">="&DATE(2026,8,1), '📉 Gastos'!A:A, "<="&EOMONTH(DATE(2026,8,1),0)) | E17: =C17-D17 | F17: =SUMIFS('💰 Ingresos'!G:G, '💰 Ingresos'!A:A, ">="&DATE(2026,8,1), '💰 Ingresos'!A:A, "<="&EOMONTH(DATE(2026,8,1),0)) | G17: =SUMIFS('📉 Gastos'!F:F, '📉 Gastos'!A:A, ">="&DATE(2026,8,1), '📉 Gastos'!A:A, "<="&EOMONTH(DATE(2026,8,1),0))
B18: Septiembre | C18: =SUMIFS('💰 Ingresos'!E:E, '💰 Ingresos'!A:A, ">="&DATE(2026,9,1), '💰 Ingresos'!A:A, "<="&EOMONTH(DATE(2026,9,1),0)) | D18: =SUMIFS('📉 Gastos'!E:E, '📉 Gastos'!A:A, ">="&DATE(2026,9,1), '📉 Gastos'!A:A, "<="&EOMONTH(DATE(2026,9,1),0)) | E18: =C18-D18 | F18: =SUMIFS('💰 Ingresos'!G:G, '💰 Ingresos'!A:A, ">="&DATE(2026,9,1), '💰 Ingresos'!A:A, "<="&EOMONTH(DATE(2026,9,1),0)) | G18: =SUMIFS('📉 Gastos'!F:F, '📉 Gastos'!A:A, ">="&DATE(2026,9,1), '📉 Gastos'!A:A, "<="&EOMONTH(DATE(2026,9,1),0))
B19: Octubre | C19: =SUMIFS('💰 Ingresos'!E:E, '💰 Ingresos'!A:A, ">="&DATE(2026,10,1), '💰 Ingresos'!A:A, "<="&EOMONTH(DATE(2026,10,1),0)) | D19: =SUMIFS('📉 Gastos'!E:E, '📉 Gastos'!A:A, ">="&DATE(2026,10,1), '📉 Gastos'!A:A, "<="&EOMONTH(DATE(2026,10,1),0)) | E19: =C19-D19 | F19: =SUMIFS('💰 Ingresos'!G:G, '💰 Ingresos'!A:A, ">="&DATE(2026,10,1), '💰 Ingresos'!A:A, "<="&EOMONTH(DATE(2026,10,1),0)) | G19: =SUMIFS('📉 Gastos'!F:F, '📉 Gastos'!A:A, ">="&DATE(2026,10,1), '📉 Gastos'!A:A, "<="&EOMONTH(DATE(2026,10,1),0))
B20: Noviembre | C20: =SUMIFS('💰 Ingresos'!E:E, '💰 Ingresos'!A:A, ">="&DATE(2026,11,1), '💰 Ingresos'!A:A, "<="&EOMONTH(DATE(2026,11,1),0)) | D20: =SUMIFS('📉 Gastos'!E:E, '📉 Gastos'!A:A, ">="&DATE(2026,11,1), '📉 Gastos'!A:A, "<="&EOMONTH(DATE(2026,11,1),0)) | E20: =C20-D20 | F20: =SUMIFS('💰 Ingresos'!G:G, '💰 Ingresos'!A:A, ">="&DATE(2026,11,1), '💰 Ingresos'!A:A, "<="&EOMONTH(DATE(2026,11,1),0)) | G20: =SUMIFS('📉 Gastos'!F:F, '📉 Gastos'!A:A, ">="&DATE(2026,11,1), '📉 Gastos'!A:A, "<="&EOMONTH(DATE(2026,11,1),0))
B21: Diciembre | C21: =SUMIFS('💰 Ingresos'!E:E, '💰 Ingresos'!A:A, ">="&DATE(2026,12,1), '💰 Ingresos'!A:A, "<="&EOMONTH(DATE(2026,12,1),0)) | D21: =SUMIFS('📉 Gastos'!E:E, '📉 Gastos'!A:A, ">="&DATE(2026,12,1), '📉 Gastos'!A:A, "<="&EOMONTH(DATE(2026,12,1),0)) | E21: =C21-D21 | F21: =SUMIFS('💰 Ingresos'!G:G, '💰 Ingresos'!A:A, ">="&DATE(2026,12,1), '💰 Ingresos'!A:A, "<="&EOMONTH(DATE(2026,12,1),0)) | G21: =SUMIFS('📉 Gastos'!F:F, '📉 Gastos'!A:A, ">="&DATE(2026,12,1), '📉 Gastos'!A:A, "<="&EOMONTH(DATE(2026,12,1),0))
B22: TOTAL ANUAL | C22: =SUM(C10:C21) | D22: =SUM(D10:D21) | E22: =SUM(E10:E21) | F22: =SUM(F10:F21) | G22: =SUM(G10:G21)

Sheet 💰 Ingresos
B2: REGISTRO DE FACTURAS EMITIDAS
A4: Fecha | B4: Nº Factura | C4: Cliente | D4: Concepto | E4: Base Imponible (€) | F4: % IVA | G4: Cuota IVA (€) | H4: % IRPF | I4: Retención IRPF (€) | J4: Total Factura (€)
A5: 2026-01-15 | B5: FAC-2026-001 | C5: Acme Corp S.L. | D5: Consultoría Estratégica Enero | E5: 1500 | F5: 0.21 | G5: =E5*F5 | H5: 0.15 | I5: =E5*H5 | J5: =E5+G5-I5
A6: 2026-01-28 | B6: FAC-2026-002 | C6: Studio Design S.L. | D6: Desarrollo Web Frontend | E6: 2200 | F6: 0.21 | G6: =E6*F6 | H6: 0.15 | I6: =E6*H6 | J6: =E6+G6-I6
A7: 2026-02-10 | B7: FAC-2026-003 | C7: Innovatech Europa | D7: Mantenimiento Mensual | E7: 800 | F7: 0.21 | G7: =E7*F7 | H7: 0.07 | I7: =E7*H7 | J7: =E7+G7-I7

Sheet 📉 Gastos
B2: REGISTRO DE GASTOS Y DEDUCCIONES
A4: Fecha | B4: Nº Factura / Ticket | C4: Proveedor | D4: Categoría Deducible | E4: Base Imponible (€) | F4: IVA Deducible (€) | G4: Total Pagado (€)
A5: 2026-01-05 | B5: EXP-01 | C5: Seguridad Social | D5: Cuota Autónomos | E5: 294 | F5: 0 | G5: 294
A6: 2026-01-10 | B6: EXP-02 | C6: Adobe Creative Cloud | D6: Software / SaaS | E6: 62.99 | F6: 13.23 | G6: 76.22
A7: 2026-01-20 | B7: EXP-03 | C7: Asesoría Fiscal Online | D7: Gestoría / Legal | E7: 75 | F7: 15.75 | G7: 90.75
A8: 2026-01-25 | B8: EXP-04 | C8: Vodafone Fibra | D8: Suministros (Luz/Internet) | E8: 45 | F8: 9.45 | G8: 54.45
